ursa/__init__.py
ursa/bls.py
ursa/indy_error.py
ursa/lib.py
python_ursa-0.1.1.dist-info/LICENSE
python_ursa-0.1.1.dist-info/METADATA
python_ursa-0.1.1.dist-info/WHEEL
python_ursa-0.1.1.dist-info/top_level.txt
python_ursa-0.1.1.dist-info/RECORD
