Metadata-Version: 2.1
Name: python-ursa
Version: 0.1.1
Summary: python wrapper for ursa universal crypto library
Home-page: https://github.com/hyperledger/ursa-python
Author: Cam Parra, Vyacheslav Gudkov
Author-email: camilo.parra@evernym.com, vyacheslav.gudkov@dsr-company.com
License: Apache-2.0
Platform: UNKNOWN
Classifier: Programming Language :: Python :: 3
Classifier: License :: OSI Approved :: Apache Software License
Classifier: Operating System :: OS Independent
Requires-Dist: pytest
